LICENSE
MANIFEST.in
README.md
package.json
setup.py
dash_jsme/DashJsme.py
dash_jsme/__init__.py
dash_jsme/_imports_.py
dash_jsme/dash_jsme.min.js
dash_jsme/dash_jsme.min.js.map
dash_jsme/metadata.json
dash_jsme/package-info.json
dash_jsme.egg-info/PKG-INFO
dash_jsme.egg-info/SOURCES.txt
dash_jsme.egg-info/dependency_links.txt
dash_jsme.egg-info/top_level.txt