Metadata-Version: 1.1
Name: dash-jsme
Version: 0.0.3
Summary: Project Description
Home-page: UNKNOWN
Author: Daniel Korn <dkorn@cs.unc.edu>
Author-email: UNKNOWN
License: MIT
Platform: UNKNOWN
Classifier: Framework :: Dash
